ldas/__init__.py
ldas/_modidx.py
ldas/core.py
ldas/iiif.py
ldas/svg.py
ldas-0.0.8.dist-info/LICENSE
ldas-0.0.8.dist-info/METADATA
ldas-0.0.8.dist-info/WHEEL
ldas-0.0.8.dist-info/entry_points.txt
ldas-0.0.8.dist-info/top_level.txt
ldas-0.0.8.dist-info/RECORD
